Metadata-Version: 1.0
Name: math-learn
Version: 0.2
Summary: Math manipulation library
Home-page: UNKNOWN
Author: Usman IlamDin
Author-email: usmanilamdin65@gmail.com
License: UNKNOWN
Platform: UNKNOWN
